{
  "firstLayout": "",
  "gdVersion": {
    "build": 99,
    "major": 4,
    "minor": 0,
    "revision": 0
  },
  "properties": {
    "adaptGameResolutionAtRuntime": true,
    "antialiasingMode": "MSAA",
    "antialisingEnabledOnMobile": false,
    "folderProject": true,
    "orientation": "landscape",
    "packageName": "com.example.gamename",
    "pixelsRounding": false,
    "projectUuid": "c7f71288-0839-4982-a53e-2923fb5dd2e1",
    "scaleMode": "linear",
    "sizeOnStartupMode": "adaptWidth",
    "templateSlug": "",
    "useExternalSourceFiles": false,
    "version": "1.0.0",
    "name": "Cafe Simulator",
    "description": "",
    "author": "",
    "windowWidth": 1280,
    "windowHeight": 720,
    "latestCompilationDirectory": "",
    "maxFPS": 75,
    "minFPS": 30,
    "verticalSync": false,
    "platformSpecificAssets": {},
    "loadingScreen": {
      "backgroundColor": 0,
      "backgroundFadeInDuration": 0.2,
      "backgroundImageResourceName": "",
      "gdevelopLogoStyle": "light",
      "logoAndProgressFadeInDuration": 0.2,
      "logoAndProgressLogoFadeInDelay": 0.2,
      "minDuration": 1.5,
      "progressBarColor": 16777215,
      "progressBarHeight": 20,
      "progressBarMaxWidth": 200,
      "progressBarMinWidth": 40,
      "progressBarWidthPercent": 30,
      "showGDevelopSplash": true,
      "showProgressBar": true
    },
    "watermark": {
      "placement": "bottom-left",
      "showWatermark": true
    },
    "authorIds": [],
    "authorUsernames": [],
    "categories": [],
    "playableDevices": [],
    "extensionProperties": [],
    "platforms": [
      {
        "name": "GDevelop JS platform"
      }
    ],
    "currentPlatform": "GDevelop JS platform"
  },
  "resources": {
    "resources": [
      {
        "alwaysLoaded": false,
        "file": "assets/Coffee Bag.png",
        "kind": "image",
        "metadata": "",
        "name": "Coffee Bag.png",
        "smoothed": false,
        "userAdded": false,
        "origin": {
          "identifier": "https://asset-resources.gdevelop.io/public-resources/32x32 Pixel art items/Pixel Mart/Food/2ea14f0f416d2fe48fcc892a2792065db5b2a9f1a2b8b8977dedfc22d29a0bad_Coffee Bag.png",
          "name": "Coffee Bag.png"
        }
      },
      {
        "alwaysLoaded": false,
        "file": "assets/Sugar.png",
        "kind": "image",
        "metadata": "",
        "name": "Sugar.png",
        "smoothed": false,
        "userAdded": false,
        "origin": {
          "identifier": "https://asset-resources.gdevelop.io/public-resources/32x32 Pixel art items/Pixel Mart/Food/00cce86b9d49668a9a3cc1a14c91378d449f42f21f8f0e826c4373eb92c91d2e_Sugar.png",
          "name": "Sugar.png"
        }
      },
      {
        "file": "assets/Whipped Cream.glb",
        "kind": "model3D",
        "metadata": "",
        "name": "Whipped Cream.glb",
        "userAdded": false,
        "origin": {
          "identifier": "https://asset-resources.gdevelop.io/public-resources/3D Food/Food/ddc463e298ed4d609d4bd51a24dfbcfe021cd30115eef19d4a9e0839631f61a3_Whipped Cream.glb",
          "name": "Whipped Cream.glb"
        }
      },
      {
        "alwaysLoaded": false,
        "file": "assets/Milk Plastic.png",
        "kind": "image",
        "metadata": "",
        "name": "Milk Plastic.png",
        "smoothed": false,
        "userAdded": false,
        "origin": {
          "identifier": "https://asset-resources.gdevelop.io/public-resources/32x32 Pixel art items/Pixel Mart/Drink/63952332ad63db4b96235e11ffe52146bcbb20bb99b8de018ee7073de9c8cfb2_Milk Plastic.png",
          "name": "Milk Plastic.png"
        }
      },
      {
        "alwaysLoaded": false,
        "file": "assets/Chocolatecake.png",
        "kind": "image",
        "metadata": "",
        "name": "Chocolatecake.png",
        "smoothed": false,
        "userAdded": false,
        "origin": {
          "identifier": "https://asset-resources.gdevelop.io/public-resources/32x32 Pixel art items/Pixel Food/Food/d59a7048fd147b14b1b1ae1e512864fb3e15049819c2f58ffa5e2117bd941413_Chocolatecake.png",
          "name": "Chocolatecake.png"
        }
      },
      {
        "file": "assets/Cup Tea.glb",
        "kind": "model3D",
        "metadata": "",
        "name": "Cup Tea.glb",
        "userAdded": false,
        "origin": {
          "identifier": "https://asset-resources.gdevelop.io/public-resources/3D Food/Drink/6178ecef7660da5b25d12ade0ed878bf5023ecd7d5fe18c260ffb8b9dd00cf73_Cup Tea.glb",
          "name": "Cup Tea.glb"
        }
      },
      {
        "file": "assets/Kitchen Coffee Machine.glb",
        "kind": "model3D",
        "metadata": "",
        "name": "Kitchen Coffee Machine.glb",
        "userAdded": false,
        "origin": {
          "identifier": "https://asset-resources.gdevelop.io/public-resources/3D Furniture/device/afa33ee7785c000c9b7387887bbc20c9e1b6fac47c4753e2dca48853655d5db3_Kitchen Coffee Machine.glb",
          "name": "Kitchen Coffee Machine.glb"
        }
      },
      {
        "file": "assets/Counter Straight2.glb",
        "kind": "model3D",
        "metadata": "",
        "name": "Counter Straight.glb",
        "userAdded": false,
        "origin": {
          "identifier": "https://asset-resources.gdevelop.io/public-resources/3D Sushi Restaurant/Furniture/1fad36af9b1193673c5194a22410405c2121a1af7201c15f83d1f39cedb01711_Counter Straight.glb",
          "name": "Counter Straight.glb"
        }
      },
      {
        "alwaysLoaded": false,
        "file": "assets/tiled_Brown Background.png",
        "kind": "image",
        "metadata": "",
        "name": "tiled_Brown Background.png",
        "smoothed": true,
        "userAdded": false,
        "origin": {
          "identifier": "https://asset-resources.gdevelop.io/public-resources/Rolling Ball Pack/Background/627c085f02e0d1fa600f2d47ada863d1176a33dd54e051ddcf3e9ccfb2190a88_tiled_Brown Background.png",
          "name": "tiled_Brown Background.png"
        }
      },
      {
        "alwaysLoaded": false,
        "file": "assets/tiled_Brown Background.png2.png",
        "kind": "image",
        "metadata": "{\"extension\":\".png\",\"pskl\":{}}",
        "name": "tiled_Brown Background.png2",
        "smoothed": true,
        "userAdded": false
      },
      {
        "alwaysLoaded": false,
        "file": "Untitled_Artwork.png",
        "kind": "image",
        "metadata": "{\"localFilePath\":\"Untitled_Artwork.png\",\"extension\":\".png\"}",
        "name": "Untitled_Artwork.png",
        "smoothed": true,
        "userAdded": true
      },
      {
        "alwaysLoaded": false,
        "file": "Untitled_Artwork2.png",
        "kind": "image",
        "metadata": "",
        "name": "Untitled_Artwork2.png",
        "smoothed": true,
        "userAdded": false
      },
      {
        "alwaysLoaded": false,
        "file": "Untitled_Artwork 2.png",
        "kind": "image",
        "metadata": "",
        "name": "Untitled_Artwork 2.png",
        "smoothed": true,
        "userAdded": true
      },
      {
        "alwaysLoaded": false,
        "file": "Untitled_Artwork 3.png",
        "kind": "image",
        "metadata": "",
        "name": "Untitled_Artwork 3.png",
        "smoothed": true,
        "userAdded": true
      },
      {
        "alwaysLoaded": false,
        "file": "Untitled_Artwork4.png",
        "kind": "image",
        "metadata": "",
        "name": "Untitled_Artwork4.png",
        "smoothed": true,
        "userAdded": true
      },
      {
        "alwaysLoaded": false,
        "file": "Untitled_Artwork 4.png",
        "kind": "image",
        "metadata": "",
        "name": "Untitled_Artwork 4.png",
        "smoothed": true,
        "userAdded": true
      },
      {
        "alwaysLoaded": false,
        "file": "Untitled_Artwork5.png",
        "kind": "image",
        "metadata": "",
        "name": "Untitled_Artwork5.png",
        "smoothed": true,
        "userAdded": true
      },
      {
        "alwaysLoaded": false,
        "file": "Untitled_Artwork 5.png",
        "kind": "image",
        "metadata": "",
        "name": "Untitled_Artwork 5.png",
        "smoothed": true,
        "userAdded": false
      }
    ],
    "resourceFolders": []
  },
  "objects": [],
  "objectsFolderStructure": {
    "folderName": "__ROOT"
  },
  "objectsGroups": [],
  "variables": [],
  "layouts": [
    {
      "__REFERENCE_TO_SPLIT_OBJECT": true,
      "referenceTo": "/layouts/making-latte"
    },
    {
      "__REFERENCE_TO_SPLIT_OBJECT": true,
      "referenceTo": "/layouts/untitled-scene"
    }
  ],
  "externalEvents": [
    {
      "__REFERENCE_TO_SPLIT_OBJECT": true,
      "referenceTo": "/externalEvents/untitled-external-events"
    }
  ],
  "eventsFunctionsExtensions": [],
  "externalLayouts": [],
  "externalSourceFiles": []
}